{"entity":{"id":"hei_ex_000591","slug":"bitglobal","canonical_name":"BitGlobal","aliases":["Bithumb Global"],"type":"cex","status":"inactive","death_reason":null,"launch_date":"2019-05-13","death_date":null,"country_or_origin":"Hong Kong / global","summary":"Global centralized exchange launched in 2019 and later renamed BitGlobal.","official_url_original":"https://www.bitglobal.com/","official_domain_original":"bitglobal.com","official_url_status":"unknown","archived_url":"https://web.archive.org/web/*/https://www.bitglobal.com/","predecessor_id":null,"successor_id":null,"confidence":"medium","last_verified_at":"2026-07-03","notes":"Separate from the Korean Bithumb exchange; no reliable final shutdown date was recovered."},"events":[],"evidence":[]}